django_requests_api-0.6.0.dist-info/licenses/LICENSE
requests_api/__init__.py
requests_api/apps.py
requests_api/requests_api.py
django_requests_api-0.6.0.dist-info/METADATA
django_requests_api-0.6.0.dist-info/WHEEL
django_requests_api-0.6.0.dist-info/top_level.txt
django_requests_api-0.6.0.dist-info/RECORD
