Metadata-Version: 2.4
Name: django-requests-api
Version: 0.6.0
Summary: Django''s application to provide simple and shared requests client.
Home-page: https://github.com/DLRSP/django-requests-api
Author: DLRSP
Author-email: dlrsp.dev@gmail.com
License: MIT License
Keywords: django,requests,API,privacy,cookie
Classifier: Development Status :: 4 - Beta
Classifier: Environment :: Web Environment
Classifier: Framework :: Django
Classifier: Framework :: Django :: 3.2
Classifier: Framework :: Django :: 4.2
Classifier: Intended Audience :: Developers
Classifier: License :: OSI Approved :: MIT License
Classifier: Operating System :: OS Independent
Classifier: Programming Language :: Python
Classifier: Programming Language :: Python :: 3
Classifier: Programming Language :: Python :: 3 :: Only
Classifier: Programming Language :: Python :: 3.8
Classifier: Programming Language :: Python :: 3.9
Classifier: Programming Language :: Python :: 3.10
Classifier: Programming Language :: Python :: 3.11
Classifier: Operating System :: OS Independent
Classifier: Topic :: Internet :: WWW/HTTP
Classifier: Topic :: Internet :: WWW/HTTP :: Dynamic Content
Classifier: Topic :: Internet :: WWW/HTTP :: WSGI :: Application
Classifier: Topic :: Software Development :: Libraries :: Application Frameworks
Classifier: Topic :: Software Development :: Libraries
Requires-Python: >=3.8
License-File: LICENSE
Requires-Dist: Django>=3.2
Provides-Extra: testing
Requires-Dist: coverage; extra == "testing"
Requires-Dist: codecov; extra == "testing"
Provides-Extra: linting
Requires-Dist: flake8; extra == "linting"
Requires-Dist: pylint; extra == "linting"
Dynamic: license-file
